gateau_api/__init__.py
gateau_api/api.py
gateau_api/constants.py
gateau_api/dependencies/__init__.py
gateau_api/dependencies/service.py
gateau_api/dependencies/user.py
gateau_api/exceptions.py
gateau_api/firebase.py
gateau_api/game_ram/__init__.py
gateau_api/game_ram/cartridge_info.py
gateau_api/game_ram/carts.py
gateau_api/game_ram/pokemon/__init__.py
gateau_api/game_ram/pokemon/constants.py
gateau_api/game_ram/pokemon/crystal.py
gateau_api/game_ram/pokemon/gold_silver.py
gateau_api/game_ram/pokemon/red_blue.py
gateau_api/routers/__init__.py
gateau_api/routers/admin_authed.py
gateau_api/routers/firebase_authed.py
gateau_api/routers/unauthed.py
gateau_api/scripts/__init__.py
gateau_api/scripts/make_admin.py
gateau_api/service.py
gateau_api/types.py
gateau_api-0.19.0.dist-info/LICENSE.md
gateau_api-0.19.0.dist-info/WHEEL
gateau_api-0.19.0.dist-info/METADATA
gateau_api-0.19.0.dist-info/RECORD
