Metadata-Version: 2.1
Name: gateau-api
Version: 0.19.0
Summary: 
Author: Kevin Duff
Author-email: kevinkelduff@gmail.com
Requires-Python: >=3.9,<4.0
Classifier: Programming Language :: Python :: 3
Classifier: Programming Language :: Python :: 3.10
Classifier: Programming Language :: Python :: 3.9
Requires-Dist: bidict (>=0.21.4,<0.22.0)
Requires-Dist: click (>=8.1.2,<9.0.0)
Requires-Dist: fastapi (>=0.71.0,<0.72.0)
Requires-Dist: fastapi-camelcase (>=1.0.5,<2.0.0)
Requires-Dist: firebase-admin (>=5.2.0,<6.0.0)
Requires-Dist: firebasil (>=0.1.4,<0.2.0)
Requires-Dist: uvicorn (>=0.16.0,<0.17.0)
